{
  "extends": ["tslint:recommended", "tslint-react", "tslint-config-prettier"],
  "tslint.enable": true,
  "tslint.alwaysShowRuleFailuresAsWarnings": true,
  "defaultSeverity": "warn",
  "rules": {
    "await-promise": true,
    "curly": [true, "ignore-same-line"],
    "interface-name": [true, "never-prefix"],
    "jsx-alignment": false,
    "jsx-boolean-value": {
      "severity": "default"
    },
    "jsx-no-bind": {
      "severity": "warn"
    },
    "jsx-no-lambda": false,
    "jsx-no-multiline-js": false,
    "jsx-wrap-multiline": false,
    "member-access": false,
    "member-ordering": {
      "options": {
        "order": "instance-sandwich"
      },
      "severity": "default"
    },
    "no-console": false,
    "no-empty": {
      "severity": "default"
    },
    "no-empty-interface": {
      "severity": "warn"
    },
    "no-return-await": true,
    "no-unused-expression": [true, "allow-fast-null-checks"],
    "no-unused-variable": true,
    "object-literal-sort-keys": false,
    "ordered-imports": [
      true,
      {
        "named-imports-order": "lowercase-first"
      }
    ],
    "promise-function-async": false,
    "semicolon": false,
    "strict-type-predicates": true
  }
}
